mqtt_router/__init__.py
mqtt_router/converters.py
mqtt_router/router.py
mqtt_router-0.1.3.dist-info/LICENSE
mqtt_router-0.1.3.dist-info/METADATA
mqtt_router-0.1.3.dist-info/WHEEL
mqtt_router-0.1.3.dist-info/top_level.txt
mqtt_router-0.1.3.dist-info/RECORD
