Metadata-Version: 2.1
Name: mqtt-router
Version: 0.1.3
Summary: Simple client agnostic MQTT message router
Home-page: https://github.com/abdellatifLabr/mqtt-router
Author: Abdellatif Labreche
Author-email: abdellatif.labreche@gmail.com
Classifier: Programming Language :: Python :: 3
Classifier: License :: OSI Approved :: MIT License
Classifier: Operating System :: OS Independent
Requires-Python: >=3.6
License-File: LICENSE
